{"nodes": [{"id": 1, "x": 1.5315890905932263, "y": 1.2743385418162496, "group": 0}, {"id": 3, "x": 1.6719672530903602, "y": 1.1987880019399721, "group": 0}, {"id": 9, "x": 1.5225312887432323, "y": 1.051321371927478, "group": 0}, {"id": 15, "x": 1.5124066899095447, "y": 1.1987656657955392, "group": 0}, {"id": 24, "x": 1.6409376136171674, "y": 1.2365535123815734, "group": 0}, {"id": 2, "x": 1.571020323420799, "y": 1.1180947272855921, "group": 0}, {"id": 4, "x": 1.6262378793321204, "y": 1.1729939838152479, "group": 0}, {"id": 14, "x": 1.606753521981546, "y": 1.1087514903479663, "group": 0}, {"id": 19, "x": 1.7029710587683753, "y": 1.1502386670258613, "group": 0}, {"id": 22, "x": 1.6392853208612874, "y": 1.0353961351658105, "group": 0}, {"id": 23, "x": 1.656293860089789, "y": 0.9678387468805386, "group": 0}, {"id": 29, "x": 1.6583298599585594, "y": 1.1178596612504736, "group": 0}, {"id": 12, "x": 1.582710088187637, "y": 1.176495151357558, "group": 0}, {"id": 26, "x": 1.7072777694325039, "y": 1.0890987863610972, "group": 0}, {"id": 31, "x": 1.7269986001723638, "y": 1.2098429555378427, "group": 0}, {"id": 6, "x": 1.57301315695171, "y": 1.044734922105165, "group": 0}, {"id": 13, "x": 1.5502164226737443, "y": 0.9457618585614312, "group": 0}, {"id": 20, "x": 1.6016346214383126, "y": 0.8705309530544465, "group": 0}, {"id": 7, "x": 1.3774775905686973, "y": 1.0632954545438125, "group": 0}, {"id": 16, "x": 1.4462158797748326, "y": 1.037019177507444, "group": 0}, {"id": 21, "x": 1.4837984045483752, "y": 0.9344968411923945, "group": 0}, {"id": 30, "x": 1.3233462219301009, "y": 0.9882434008053597, "group": 0}, {"id": 8, "x": 1.5772878496081644, "y": 0.6425822676366724, "group": 0}, {"id": 0, "x": 1.473417799557213, "y": 0.7063356560452556, "group": 0}, {"id": 10, "x": 1.5761406030717116, "y": 0.7685816805582117, "group": 0}, {"id": 11, "x": 1.5250430941526043, "y": 0.845172944514215, "group": 0}, {"id": 25, "x": 1.4644047879520234, "y": 0.881177336505193, "group": 0}, {"id": 5, "x": 1.8189802407563398, "y": 1.0381453105330687, "group": 0}, {"id": 18, "x": 1.7855536257886235, "y": 1.1209881761921787, "group": 0}, {"id": 28, "x": 1.7289846364474293, "y": 1.0374189338715611, "group": 0}, {"id": 27, "x": 1.831680466047451, "y": 1.152960933188835, "group": 0}], "links": [{"source": 1, "target": 3, "weight": 1}, {"source": 1, "target": 9, "weight": 1}, {"source": 1, "target": 15, "weight": 1}, {"source": 1, "target": 24, "weight": 1}, {"source": 1, "target": 14, "weight": 1}, {"source": 3, "target": 2, "weight": 1}, {"source": 3, "target": 4, "weight": 1}, {"source": 3, "target": 12, "weight": 1}, {"source": 3, "target": 14, "weight": 1}, {"source": 3, "target": 19, "weight": 1}, {"source": 3, "target": 22, "weight": 1}, {"source": 3, "target": 24, "weight": 1}, {"source": 3, "target": 26, "weight": 1}, {"source": 3, "target": 29, "weight": 1}, {"source": 3, "target": 31, "weight": 1}, {"source": 3, "target": 15, "weight": 1}, {"source": 3, "target": 27, "weight": 1}, {"source": 3, "target": 28, "weight": 1}, {"source": 9, "target": 2, "weight": 1}, {"source": 9, "target": 6, "weight": 1}, {"source": 9, "target": 7, "weight": 1}, {"source": 9, "target": 4, "weight": 1}, {"source": 9, "target": 11, "weight": 1}, {"source": 9, "target": 13, "weight": 1}, {"source": 9, "target": 14, "weight": 1}, {"source": 9, "target": 15, "weight": 1}, {"source": 9, "target": 16, "weight": 1}, {"source": 9, "target": 20, "weight": 1}, {"source": 9, "target": 21, "weight": 1}, {"source": 9, "target": 22, "weight": 1}, {"source": 9, "target": 23, "weight": 1}, {"source": 9, "target": 29, "weight": 1}, {"source": 9, "target": 30, "weight": 1}, {"source": 9, "target": 19, "weight": 1}, {"source": 15, "target": 6, "weight": 1}, {"source": 15, "target": 14, "weight": 1}, {"source": 15, "target": 12, "weight": 1}, {"source": 15, "target": 29, "weight": 1}, {"source": 24, "target": 2, "weight": 1}, {"source": 24, "target": 12, "weight": 1}, {"source": 24, "target": 14, "weight": 1}, {"source": 24, "target": 19, "weight": 1}, {"source": 24, "target": 22, "weight": 1}, {"source": 24, "target": 4, "weight": 1}, {"source": 24, "target": 29, "weight": 1}, {"source": 24, "target": 31, "weight": 1}, {"source": 24, "target": 26, "weight": 1}, {"source": 2, "target": 4, "weight": 1}, {"source": 2, "target": 14, "weight": 1}, {"source": 2, "target": 19, "weight": 1}, {"source": 2, "target": 22, "weight": 1}, {"source": 2, "target": 23, "weight": 1}, {"source": 2, "target": 29, "weight": 1}, {"source": 2, "target": 6, "weight": 1}, {"source": 2, "target": 16, "weight": 1}, {"source": 2, "target": 26, "weight": 1}, {"source": 4, "target": 6, "weight": 1}, {"source": 4, "target": 12, "weight": 1}, {"source": 4, "target": 14, "weight": 1}, {"source": 4, "target": 19, "weight": 1}, {"source": 4, "target": 22, "weight": 1}, {"source": 4, "target": 26, "weight": 1}, {"source": 4, "target": 29, "weight": 1}, {"source": 4, "target": 31, "weight": 1}, {"source": 14, "target": 6, "weight": 1}, {"source": 14, "target": 12, "weight": 1}, {"source": 14, "target": 5, "weight": 1}, {"source": 14, "target": 7, "weight": 1}, {"source": 14, "target": 16, "weight": 1}, {"source": 14, "target": 18, "weight": 1}, {"source": 14, "target": 19, "weight": 1}, {"source": 14, "target": 22, "weight": 1}, {"source": 14, "target": 26, "weight": 1}, {"source": 14, "target": 28, "weight": 1}, {"source": 14, "target": 29, "weight": 1}, {"source": 14, "target": 31, "weight": 1}, {"source": 14, "target": 21, "weight": 1}, {"source": 19, "target": 12, "weight": 1}, {"source": 19, "target": 18, "weight": 1}, {"source": 19, "target": 22, "weight": 1}, {"source": 19, "target": 26, "weight": 1}, {"source": 19, "target": 27, "weight": 1}, {"source": 19, "target": 28, "weight": 1}, {"source": 19, "target": 29, "weight": 1}, {"source": 19, "target": 31, "weight": 1}, {"source": 22, "target": 6, "weight": 1}, {"source": 22, "target": 5, "weight": 1}, {"source": 22, "target": 10, "weight": 1}, {"source": 22, "target": 11, "weight": 1}, {"source": 22, "target": 12, "weight": 1}, {"source": 22, "target": 18, "weight": 1}, {"source": 22, "target": 23, "weight": 1}, {"source": 22, "target": 25, "weight": 1}, {"source": 22, "target": 29, "weight": 1}, {"source": 22, "target": 31, "weight": 1}, {"source": 22, "target": 26, "weight": 1}, {"source": 23, "target": 6, "weight": 1}, {"source": 23, "target": 13, "weight": 1}, {"source": 23, "target": 26, "weight": 1}, {"source": 23, "target": 28, "weight": 1}, {"source": 29, "target": 6, "weight": 1}, {"source": 29, "target": 12, "weight": 1}, {"source": 29, "target": 26, "weight": 1}, {"source": 29, "target": 27, "weight": 1}, {"source": 29, "target": 28, "weight": 1}, {"source": 29, "target": 13, "weight": 1}, {"source": 29, "target": 18, "weight": 1}, {"source": 29, "target": 31, "weight": 1}, {"source": 12, "target": 6, "weight": 1}, {"source": 12, "target": 31, "weight": 1}, {"source": 12, "target": 16, "weight": 1}, {"source": 12, "target": 26, "weight": 1}, {"source": 26, "target": 18, "weight": 1}, {"source": 26, "target": 5, "weight": 1}, {"source": 26, "target": 20, "weight": 1}, {"source": 26, "target": 27, "weight": 1}, {"source": 26, "target": 28, "weight": 1}, {"source": 26, "target": 31, "weight": 1}, {"source": 31, "target": 18, "weight": 1}, {"source": 6, "target": 13, "weight": 1}, {"source": 6, "target": 20, "weight": 1}, {"source": 13, "target": 11, "weight": 1}, {"source": 13, "target": 20, "weight": 1}, {"source": 13, "target": 25, "weight": 1}, {"source": 13, "target": 16, "weight": 1}, {"source": 20, "target": 11, "weight": 1}, {"source": 20, "target": 8, "weight": 1}, {"source": 20, "target": 25, "weight": 1}, {"source": 7, "target": 16, "weight": 1}, {"source": 7, "target": 21, "weight": 1}, {"source": 7, "target": 30, "weight": 1}, {"source": 16, "target": 21, "weight": 1}, {"source": 16, "target": 25, "weight": 1}, {"source": 16, "target": 30, "weight": 1}, {"source": 21, "target": 0, "weight": 1}, {"source": 21, "target": 10, "weight": 1}, {"source": 21, "target": 25, "weight": 1}, {"source": 21, "target": 30, "weight": 1}, {"source": 21, "target": 28, "weight": 1}, {"source": 8, "target": 0, "weight": 1}, {"source": 8, "target": 10, "weight": 1}, {"source": 0, "target": 10, "weight": 1}, {"source": 0, "target": 11, "weight": 1}, {"source": 11, "target": 25, "weight": 1}, {"source": 5, "target": 27, "weight": 1}, {"source": 5, "target": 28, "weight": 1}, {"source": 18, "target": 27, "weight": 1}, {"source": 18, "target": 28, "weight": 1}, {"source": 28, "target": 27, "weight": 1}]}