{"nodes": [{"id": 0, "x": -7.283306131735854, "y": -10.443912774047794, "group": 0}, {"id": 6, "x": -7.794666417190938, "y": -10.278432171278709, "group": 0}, {"id": 8, "x": -7.488770539235624, "y": -9.248396779744592, "group": 0}, {"id": 10, "x": -7.274334082363502, "y": -9.730254998205103, "group": 0}, {"id": 14, "x": -8.210042579515983, "y": -9.583698582177966, "group": 0}, {"id": 20, "x": -7.949970450356443, "y": -10.062373259712357, "group": 0}, {"id": 1, "x": -8.412113653224528, "y": -10.304393044691329, "group": 0}, {"id": 2, "x": -8.97670764655597, "y": -10.153304842497016, "group": 0}, {"id": 3, "x": -8.4742423088064, "y": -11.092671102048675, "group": 0}, {"id": 4, "x": -9.106991639478679, "y": -10.489078470079933, "group": 0}, {"id": 5, "x": -8.690999483396778, "y": -10.429418194604956, "group": 0}, {"id": 7, "x": -8.589735863525865, "y": -10.123635630044367, "group": 0}, {"id": 9, "x": -8.10879371333292, "y": -10.288981917524747, "group": 0}, {"id": 11, "x": -7.3899918048940085, "y": -10.113830814201537, "group": 0}, {"id": 12, "x": -7.8948728175409935, "y": -11.09385738927636, "group": 0}, {"id": 13, "x": -8.655412105812996, "y": -9.873311821958074, "group": 0}, {"id": 15, "x": -7.978814891660501, "y": -10.499510128697048, "group": 0}, {"id": 16, "x": -8.13431532849952, "y": -10.77117534542515, "group": 0}, {"id": 18, "x": -7.663572289565169, "y": -9.628942770197893, "group": 0}, {"id": 19, "x": -8.836687735895863, "y": -10.789533490018519, "group": 0}, {"id": 21, "x": -8.365708269082289, "y": -9.83480076950937, "group": 0}, {"id": 22, "x": -8.203186530682519, "y": -10.051848274751181, "group": 0}, {"id": 23, "x": -7.675121880424748, "y": -9.965906441051205, "group": 0}, {"id": 24, "x": -8.504184480364833, "y": -10.746457222893923, "group": 0}, {"id": 25, "x": -7.9135720457976415, "y": -9.442322301877347, "group": 0}, {"id": 26, "x": -7.745604123844733, "y": -10.7348838115012, "group": 0}, {"id": 27, "x": -7.58539573389029, "y": -10.464398196497571, "group": 0}, {"id": 28, "x": -8.295943117141656, "y": -10.53649208301079, "group": 0}, {"id": 29, "x": -8.558499234673592, "y": -9.460117641419, "group": 0}, {"id": 30, "x": -9.034233476591924, "y": -9.70949448109447, "group": 0}, {"id": 31, "x": -8.033591468550053, "y": -9.811675480920494, "group": 0}, {"id": 17, "x": -6.599273639895384, "y": -10.16096432088678, "group": 0}], "links": [{"source": 0, "target": 6, "weight": 4}, {"source": 0, "target": 8, "weight": 1}, {"source": 0, "target": 10, "weight": 2}, {"source": 0, "target": 14, "weight": 2}, {"source": 0, "target": 20, "weight": 4}, {"source": 0, "target": 1, "weight": 4}, {"source": 0, "target": 9, "weight": 4}, {"source": 0, "target": 11, "weight": 4}, {"source": 0, "target": 13, "weight": 4}, {"source": 0, "target": 15, "weight": 4}, {"source": 0, "target": 21, "weight": 3}, {"source": 0, "target": 22, "weight": 4}, {"source": 0, "target": 24, "weight": 4}, {"source": 0, "target": 25, "weight": 4}, {"source": 0, "target": 27, "weight": 4}, {"source": 0, "target": 28, "weight": 4}, {"source": 0, "target": 31, "weight": 4}, {"source": 6, "target": 1, "weight": 4}, {"source": 6, "target": 2, "weight": 3}, {"source": 6, "target": 5, "weight": 4}, {"source": 6, "target": 3, "weight": 3}, {"source": 6, "target": 4, "weight": 3}, {"source": 6, "target": 7, "weight": 4}, {"source": 6, "target": 9, "weight": 2}, {"source": 6, "target": 10, "weight": 4}, {"source": 6, "target": 11, "weight": 5}, {"source": 6, "target": 12, "weight": 3}, {"source": 6, "target": 13, "weight": 2}, {"source": 6, "target": 14, "weight": 3}, {"source": 6, "target": 15, "weight": 3}, {"source": 6, "target": 16, "weight": 4}, {"source": 6, "target": 18, "weight": 4}, {"source": 6, "target": 19, "weight": 3}, {"source": 6, "target": 20, "weight": 3}, {"source": 6, "target": 21, "weight": 4}, {"source": 6, "target": 22, "weight": 3}, {"source": 6, "target": 23, "weight": 3}, {"source": 6, "target": 24, "weight": 4}, {"source": 6, "target": 25, "weight": 4}, {"source": 6, "target": 26, "weight": 4}, {"source": 6, "target": 28, "weight": 4}, {"source": 6, "target": 29, "weight": 3}, {"source": 6, "target": 30, "weight": 3}, {"source": 6, "target": 31, "weight": 4}, {"source": 6, "target": 8, "weight": 3}, {"source": 8, "target": 9, "weight": 4}, {"source": 8, "target": 10, "weight": 3}, {"source": 8, "target": 11, "weight": 3}, {"source": 8, "target": 18, "weight": 3}, {"source": 8, "target": 20, "weight": 3}, {"source": 8, "target": 21, "weight": 4}, {"source": 8, "target": 23, "weight": 5}, {"source": 8, "target": 25, "weight": 3}, {"source": 8, "target": 31, "weight": 4}, {"source": 8, "target": 14, "weight": 4}, {"source": 8, "target": 15, "weight": 4}, {"source": 8, "target": 22, "weight": 4}, {"source": 10, "target": 7, "weight": 4}, {"source": 10, "target": 9, "weight": 4}, {"source": 10, "target": 11, "weight": 4}, {"source": 10, "target": 18, "weight": 4}, {"source": 10, "target": 20, "weight": 4}, {"source": 10, "target": 14, "weight": 4}, {"source": 10, "target": 15, "weight": 4}, {"source": 10, "target": 21, "weight": 4}, {"source": 10, "target": 22, "weight": 4}, {"source": 10, "target": 27, "weight": 4}, {"source": 10, "target": 28, "weight": 4}, {"source": 10, "target": 31, "weight": 4}, {"source": 14, "target": 1, "weight": 3}, {"source": 14, "target": 2, "weight": 2}, {"source": 14, "target": 5, "weight": 3}, {"source": 14, "target": 7, "weight": 4}, {"source": 14, "target": 9, "weight": 3}, {"source": 14, "target": 3, "weight": 1}, {"source": 14, "target": 4, "weight": 2}, {"source": 14, "target": 11, "weight": 4}, {"source": 14, "target": 12, "weight": 2}, {"source": 14, "target": 13, "weight": 4}, {"source": 14, "target": 15, "weight": 4}, {"source": 14, "target": 16, "weight": 4}, {"source": 14, "target": 18, "weight": 4}, {"source": 14, "target": 19, "weight": 1}, {"source": 14, "target": 20, "weight": 4}, {"source": 14, "target": 21, "weight": 4}, {"source": 14, "target": 22, "weight": 4}, {"source": 14, "target": 23, "weight": 4}, {"source": 14, "target": 24, "weight": 2}, {"source": 14, "target": 25, "weight": 4}, {"source": 14, "target": 26, "weight": 4}, {"source": 14, "target": 27, "weight": 4}, {"source": 14, "target": 28, "weight": 4}, {"source": 14, "target": 29, "weight": 2}, {"source": 14, "target": 30, "weight": 4}, {"source": 14, "target": 31, "weight": 3}, {"source": 20, "target": 1, "weight": 4}, {"source": 20, "target": 7, "weight": 4}, {"source": 20, "target": 9, "weight": 4}, {"source": 20, "target": 11, "weight": 2}, {"source": 20, "target": 13, "weight": 2}, {"source": 20, "target": 15, "weight": 4}, {"source": 20, "target": 16, "weight": 4}, {"source": 20, "target": 18, "weight": 4}, {"source": 20, "target": 2, "weight": 4}, {"source": 20, "target": 3, "weight": 4}, {"source": 20, "target": 4, "weight": 4}, {"source": 20, "target": 5, "weight": 4}, {"source": 20, "target": 12, "weight": 4}, {"source": 20, "target": 19, "weight": 4}, {"source": 20, "target": 21, "weight": 4}, {"source": 20, "target": 22, "weight": 4}, {"source": 20, "target": 23, "weight": 4}, {"source": 20, "target": 25, "weight": 2}, {"source": 20, "target": 26, "weight": 5}, {"source": 20, "target": 27, "weight": 4}, {"source": 20, "target": 28, "weight": 4}, {"source": 20, "target": 29, "weight": 4}, {"source": 20, "target": 30, "weight": 4}, {"source": 20, "target": 31, "weight": 4}, {"source": 1, "target": 2, "weight": 4}, {"source": 1, "target": 3, "weight": 3}, {"source": 1, "target": 4, "weight": 4}, {"source": 1, "target": 5, "weight": 4}, {"source": 1, "target": 7, "weight": 4}, {"source": 1, "target": 9, "weight": 3}, {"source": 1, "target": 11, "weight": 4}, {"source": 1, "target": 12, "weight": 4}, {"source": 1, "target": 13, "weight": 4}, {"source": 1, "target": 15, "weight": 1}, {"source": 1, "target": 16, "weight": 3}, {"source": 1, "target": 18, "weight": 4}, {"source": 1, "target": 19, "weight": 4}, {"source": 1, "target": 21, "weight": 4}, {"source": 1, "target": 22, "weight": 4}, {"source": 1, "target": 23, "weight": 4}, {"source": 1, "target": 24, "weight": 3}, {"source": 1, "target": 25, "weight": 4}, {"source": 1, "target": 26, "weight": 4}, {"source": 1, "target": 27, "weight": 4}, {"source": 1, "target": 28, "weight": 4}, {"source": 1, "target": 29, "weight": 3}, {"source": 1, "target": 30, "weight": 4}, {"source": 1, "target": 31, "weight": 4}, {"source": 2, "target": 3, "weight": 3}, {"source": 2, "target": 4, "weight": 3}, {"source": 2, "target": 9, "weight": 3}, {"source": 2, "target": 13, "weight": 4}, {"source": 2, "target": 15, "weight": 4}, {"source": 2, "target": 19, "weight": 3}, {"source": 2, "target": 22, "weight": 2}, {"source": 2, "target": 23, "weight": 3}, {"source": 2, "target": 24, "weight": 3}, {"source": 2, "target": 26, "weight": 3}, {"source": 2, "target": 29, "weight": 3}, {"source": 2, "target": 31, "weight": 4}, {"source": 2, "target": 5, "weight": 4}, {"source": 2, "target": 7, "weight": 4}, {"source": 2, "target": 16, "weight": 4}, {"source": 2, "target": 21, "weight": 4}, {"source": 2, "target": 28, "weight": 4}, {"source": 3, "target": 7, "weight": 4}, {"source": 3, "target": 13, "weight": 4}, {"source": 3, "target": 15, "weight": 3}, {"source": 3, "target": 16, "weight": 4}, {"source": 3, "target": 21, "weight": 4}, {"source": 3, "target": 22, "weight": 4}, {"source": 3, "target": 24, "weight": 2}, {"source": 3, "target": 27, "weight": 3}, {"source": 3, "target": 28, "weight": 3}, {"source": 3, "target": 31, "weight": 3}, {"source": 4, "target": 5, "weight": 4}, {"source": 4, "target": 9, "weight": 4}, {"source": 4, "target": 13, "weight": 4}, {"source": 4, "target": 15, "weight": 4}, {"source": 4, "target": 16, "weight": 4}, {"source": 4, "target": 21, "weight": 4}, {"source": 4, "target": 22, "weight": 3}, {"source": 4, "target": 24, "weight": 4}, {"source": 4, "target": 28, "weight": 4}, {"source": 4, "target": 31, "weight": 3}, {"source": 5, "target": 9, "weight": 4}, {"source": 5, "target": 11, "weight": 4}, {"source": 5, "target": 12, "weight": 4}, {"source": 5, "target": 15, "weight": 4}, {"source": 5, "target": 16, "weight": 4}, {"source": 5, "target": 18, "weight": 3}, {"source": 5, "target": 19, "weight": 4}, {"source": 5, "target": 21, "weight": 4}, {"source": 5, "target": 22, "weight": 4}, {"source": 5, "target": 23, "weight": 4}, {"source": 5, "target": 26, "weight": 3}, {"source": 5, "target": 27, "weight": 3}, {"source": 5, "target": 28, "weight": 1}, {"source": 5, "target": 29, "weight": 4}, {"source": 5, "target": 30, "weight": 4}, {"source": 5, "target": 31, "weight": 4}, {"source": 5, "target": 13, "weight": 4}, {"source": 7, "target": 9, "weight": 3}, {"source": 7, "target": 12, "weight": 4}, {"source": 7, "target": 13, "weight": 4}, {"source": 7, "target": 15, "weight": 4}, {"source": 7, "target": 16, "weight": 2}, {"source": 7, "target": 18, "weight": 4}, {"source": 7, "target": 19, "weight": 4}, {"source": 7, "target": 21, "weight": 2}, {"source": 7, "target": 22, "weight": 4}, {"source": 7, "target": 23, "weight": 4}, {"source": 7, "target": 24, "weight": 4}, {"source": 7, "target": 25, "weight": 4}, {"source": 7, "target": 26, "weight": 4}, {"source": 7, "target": 27, "weight": 4}, {"source": 7, "target": 29, "weight": 4}, {"source": 7, "target": 30, "weight": 1}, {"source": 7, "target": 31, "weight": 4}, {"source": 7, "target": 28, "weight": 4}, {"source": 9, "target": 11, "weight": 4}, {"source": 9, "target": 12, "weight": 4}, {"source": 9, "target": 13, "weight": 3}, {"source": 9, "target": 15, "weight": 3}, {"source": 9, "target": 16, "weight": 3}, {"source": 9, "target": 18, "weight": 4}, {"source": 9, "target": 19, "weight": 4}, {"source": 9, "target": 21, "weight": 2}, {"source": 9, "target": 22, "weight": 3}, {"source": 9, "target": 23, "weight": 3}, {"source": 9, "target": 24, "weight": 4}, {"source": 9, "target": 25, "weight": 4}, {"source": 9, "target": 26, "weight": 4}, {"source": 9, "target": 27, "weight": 4}, {"source": 9, "target": 28, "weight": 4}, {"source": 9, "target": 29, "weight": 3}, {"source": 9, "target": 31, "weight": 4}, {"source": 11, "target": 13, "weight": 2}, {"source": 11, "target": 18, "weight": 4}, {"source": 11, "target": 22, "weight": 3}, {"source": 11, "target": 23, "weight": 4}, {"source": 11, "target": 25, "weight": 2}, {"source": 11, "target": 26, "weight": 4}, {"source": 11, "target": 27, "weight": 4}, {"source": 11, "target": 15, "weight": 4}, {"source": 11, "target": 16, "weight": 4}, {"source": 11, "target": 21, "weight": 4}, {"source": 11, "target": 24, "weight": 4}, {"source": 11, "target": 28, "weight": 4}, {"source": 11, "target": 31, "weight": 4}, {"source": 12, "target": 15, "weight": 3}, {"source": 12, "target": 16, "weight": 4}, {"source": 12, "target": 22, "weight": 4}, {"source": 12, "target": 23, "weight": 4}, {"source": 12, "target": 24, "weight": 3}, {"source": 12, "target": 27, "weight": 4}, {"source": 12, "target": 28, "weight": 4}, {"source": 12, "target": 31, "weight": 3}, {"source": 13, "target": 15, "weight": 3}, {"source": 13, "target": 16, "weight": 3}, {"source": 13, "target": 18, "weight": 4}, {"source": 13, "target": 19, "weight": 4}, {"source": 13, "target": 21, "weight": 4}, {"source": 13, "target": 23, "weight": 4}, {"source": 13, "target": 25, "weight": 2}, {"source": 13, "target": 26, "weight": 4}, {"source": 13, "target": 27, "weight": 4}, {"source": 13, "target": 28, "weight": 4}, {"source": 13, "target": 29, "weight": 4}, {"source": 13, "target": 30, "weight": 4}, {"source": 13, "target": 22, "weight": 4}, {"source": 13, "target": 24, "weight": 4}, {"source": 13, "target": 31, "weight": 4}, {"source": 15, "target": 16, "weight": 4}, {"source": 15, "target": 18, "weight": 4}, {"source": 15, "target": 19, "weight": 4}, {"source": 15, "target": 21, "weight": 4}, {"source": 15, "target": 22, "weight": 4}, {"source": 15, "target": 24, "weight": 4}, {"source": 15, "target": 25, "weight": 4}, {"source": 15, "target": 26, "weight": 4}, {"source": 15, "target": 27, "weight": 4}, {"source": 15, "target": 28, "weight": 4}, {"source": 15, "target": 29, "weight": 3}, {"source": 15, "target": 30, "weight": 4}, {"source": 15, "target": 31, "weight": 4}, {"source": 16, "target": 18, "weight": 4}, {"source": 16, "target": 19, "weight": 4}, {"source": 16, "target": 21, "weight": 2}, {"source": 16, "target": 22, "weight": 4}, {"source": 16, "target": 23, "weight": 4}, {"source": 16, "target": 25, "weight": 4}, {"source": 16, "target": 26, "weight": 4}, {"source": 16, "target": 27, "weight": 4}, {"source": 16, "target": 28, "weight": 4}, {"source": 16, "target": 29, "weight": 4}, {"source": 16, "target": 24, "weight": 4}, {"source": 16, "target": 31, "weight": 4}, {"source": 18, "target": 21, "weight": 4}, {"source": 18, "target": 23, "weight": 4}, {"source": 18, "target": 26, "weight": 2}, {"source": 18, "target": 27, "weight": 3}, {"source": 18, "target": 28, "weight": 1}, {"source": 18, "target": 29, "weight": 3}, {"source": 18, "target": 31, "weight": 2}, {"source": 18, "target": 22, "weight": 4}, {"source": 18, "target": 25, "weight": 4}, {"source": 19, "target": 21, "weight": 4}, {"source": 19, "target": 22, "weight": 4}, {"source": 19, "target": 23, "weight": 3}, {"source": 19, "target": 24, "weight": 2}, {"source": 19, "target": 27, "weight": 3}, {"source": 19, "target": 28, "weight": 1}, {"source": 19, "target": 31, "weight": 3}, {"source": 21, "target": 22, "weight": 4}, {"source": 21, "target": 23, "weight": 4}, {"source": 21, "target": 24, "weight": 4}, {"source": 21, "target": 25, "weight": 3}, {"source": 21, "target": 26, "weight": 4}, {"source": 21, "target": 27, "weight": 4}, {"source": 21, "target": 28, "weight": 4}, {"source": 21, "target": 29, "weight": 4}, {"source": 21, "target": 31, "weight": 4}, {"source": 22, "target": 17, "weight": 4}, {"source": 22, "target": 23, "weight": 3}, {"source": 22, "target": 24, "weight": 4}, {"source": 22, "target": 25, "weight": 4}, {"source": 22, "target": 26, "weight": 4}, {"source": 22, "target": 27, "weight": 4}, {"source": 22, "target": 28, "weight": 4}, {"source": 22, "target": 29, "weight": 4}, {"source": 22, "target": 30, "weight": 4}, {"source": 22, "target": 31, "weight": 3}, {"source": 23, "target": 17, "weight": 4}, {"source": 23, "target": 25, "weight": 4}, {"source": 23, "target": 26, "weight": 4}, {"source": 23, "target": 27, "weight": 4}, {"source": 23, "target": 29, "weight": 4}, {"source": 23, "target": 31, "weight": 4}, {"source": 23, "target": 24, "weight": 4}, {"source": 23, "target": 28, "weight": 3}, {"source": 24, "target": 26, "weight": 4}, {"source": 24, "target": 29, "weight": 3}, {"source": 24, "target": 30, "weight": 4}, {"source": 24, "target": 31, "weight": 2}, {"source": 24, "target": 28, "weight": 4}, {"source": 25, "target": 26, "weight": 4}, {"source": 25, "target": 27, "weight": 4}, {"source": 25, "target": 28, "weight": 4}, {"source": 25, "target": 29, "weight": 4}, {"source": 25, "target": 31, "weight": 4}, {"source": 26, "target": 27, "weight": 2}, {"source": 26, "target": 28, "weight": 1}, {"source": 26, "target": 31, "weight": 3}, {"source": 27, "target": 17, "weight": 4}, {"source": 27, "target": 28, "weight": 1}, {"source": 27, "target": 29, "weight": 3}, {"source": 27, "target": 31, "weight": 4}, {"source": 28, "target": 29, "weight": 1}, {"source": 28, "target": 30, "weight": 4}, {"source": 28, "target": 31, "weight": 4}, {"source": 29, "target": 31, "weight": 3}, {"source": 30, "target": 31, "weight": 4}]}