{"nodes": [{"id": 1, "x": -1.1224299411615457, "y": -0.0921495569023457, "group": 0}, {"id": 0, "x": -1.2218980633037846, "y": -0.11176451707194819, "group": 0}, {"id": 2, "x": -1.0741101282734293, "y": -0.04307570921496976, "group": 0}, {"id": 3, "x": -1.0865675167030746, "y": -0.10622012378928039, "group": 0}, {"id": 4, "x": -1.0688030037604206, "y": -0.07163137489289916, "group": 0}, {"id": 6, "x": -1.1569164717301548, "y": -0.0679753722042081, "group": 0}, {"id": 7, "x": -1.1068338217281901, "y": -0.05884958148013401, "group": 0}, {"id": 9, "x": -1.1397563579485799, "y": -0.10569024811900612, "group": 0}, {"id": 11, "x": -1.15517570073511, "y": -0.11757067456510242, "group": 0}, {"id": 12, "x": -1.1139889587775662, "y": -0.1287586545949233, "group": 0}, {"id": 13, "x": -1.1074418884578492, "y": -0.10949648798549218, "group": 0}, {"id": 14, "x": -1.1606982478376031, "y": -0.04727837188739874, "group": 0}, {"id": 15, "x": -1.1422238929721629, "y": -0.08152890568148831, "group": 0}, {"id": 16, "x": -1.0901340455469577, "y": -0.06975100184056655, "group": 0}, {"id": 19, "x": -1.096221881031491, "y": -0.13616224162001012, "group": 0}, {"id": 20, "x": -1.1432492833253096, "y": -0.05195207737765, "group": 0}, {"id": 21, "x": -1.1296344244691683, "y": -0.06713054358073378, "group": 0}, {"id": 22, "x": -1.1777897429134896, "y": -0.07180966997647566, "group": 0}, {"id": 23, "x": -1.0966676516441385, "y": -0.08818292019738089, "group": 0}, {"id": 24, "x": -1.0985161398396894, "y": -0.02215093196049056, "group": 0}, {"id": 25, "x": -1.1456614740719664, "y": -0.1426083748678632, "group": 0}, {"id": 26, "x": -1.183559793539608, "y": -0.0878095364343835, "group": 0}, {"id": 27, "x": -1.1645624973457025, "y": -0.13478865724323788, "group": 0}, {"id": 28, "x": -1.1775436030509023, "y": -0.11711552310981044, "group": 0}, {"id": 29, "x": -1.1235053449304853, "y": -0.0407810199881904, "group": 0}, {"id": 30, "x": -1.1264054642766355, "y": -0.14573335889985992, "group": 0}, {"id": 31, "x": -1.1606739476257109, "y": -0.09292465676332848, "group": 0}, {"id": 5, "x": -1.077435167315206, "y": -0.12701883806403938, "group": 0}, {"id": 18, "x": -1.064099880484908, "y": -0.10214788437612186, "group": 0}, {"id": 10, "x": -1.2335733127344548, "y": -0.05884011365347941, "group": 0}, {"id": 8, "x": -1.2040196809174653, "y": -0.022283952343648453, "group": 0}, {"id": 17, "x": -1.3243701949553968, "y": -0.08078234762861086, "group": 0}], "links": [{"source": 1, "target": 0, "weight": 4}, {"source": 1, "target": 2, "weight": 4}, {"source": 1, "target": 3, "weight": 4}, {"source": 1, "target": 4, "weight": 4}, {"source": 1, "target": 6, "weight": 4}, {"source": 1, "target": 7, "weight": 4}, {"source": 1, "target": 9, "weight": 3}, {"source": 1, "target": 11, "weight": 4}, {"source": 1, "target": 12, "weight": 4}, {"source": 1, "target": 13, "weight": 4}, {"source": 1, "target": 14, "weight": 3}, {"source": 1, "target": 15, "weight": 2}, {"source": 1, "target": 16, "weight": 4}, {"source": 1, "target": 19, "weight": 4}, {"source": 1, "target": 20, "weight": 4}, {"source": 1, "target": 21, "weight": 4}, {"source": 1, "target": 22, "weight": 4}, {"source": 1, "target": 23, "weight": 4}, {"source": 1, "target": 24, "weight": 4}, {"source": 1, "target": 25, "weight": 4}, {"source": 1, "target": 26, "weight": 4}, {"source": 1, "target": 27, "weight": 4}, {"source": 1, "target": 28, "weight": 4}, {"source": 1, "target": 29, "weight": 4}, {"source": 1, "target": 30, "weight": 4}, {"source": 1, "target": 31, "weight": 4}, {"source": 0, "target": 6, "weight": 4}, {"source": 0, "target": 8, "weight": 1}, {"source": 0, "target": 9, "weight": 4}, {"source": 0, "target": 10, "weight": 3}, {"source": 0, "target": 11, "weight": 3}, {"source": 0, "target": 15, "weight": 4}, {"source": 0, "target": 20, "weight": 4}, {"source": 0, "target": 21, "weight": 3}, {"source": 0, "target": 22, "weight": 4}, {"source": 0, "target": 25, "weight": 4}, {"source": 0, "target": 26, "weight": 4}, {"source": 0, "target": 27, "weight": 4}, {"source": 0, "target": 28, "weight": 4}, {"source": 0, "target": 31, "weight": 4}, {"source": 2, "target": 3, "weight": 3}, {"source": 2, "target": 4, "weight": 3}, {"source": 2, "target": 6, "weight": 3}, {"source": 2, "target": 9, "weight": 3}, {"source": 2, "target": 13, "weight": 4}, {"source": 2, "target": 14, "weight": 2}, {"source": 2, "target": 15, "weight": 4}, {"source": 2, "target": 19, "weight": 3}, {"source": 2, "target": 22, "weight": 1}, {"source": 2, "target": 23, "weight": 3}, {"source": 2, "target": 24, "weight": 4}, {"source": 2, "target": 26, "weight": 3}, {"source": 2, "target": 29, "weight": 3}, {"source": 2, "target": 31, "weight": 4}, {"source": 2, "target": 5, "weight": 4}, {"source": 2, "target": 7, "weight": 4}, {"source": 2, "target": 12, "weight": 4}, {"source": 2, "target": 16, "weight": 3}, {"source": 2, "target": 20, "weight": 4}, {"source": 2, "target": 21, "weight": 4}, {"source": 3, "target": 4, "weight": 3}, {"source": 3, "target": 5, "weight": 4}, {"source": 3, "target": 6, "weight": 4}, {"source": 3, "target": 7, "weight": 4}, {"source": 3, "target": 9, "weight": 4}, {"source": 3, "target": 11, "weight": 4}, {"source": 3, "target": 12, "weight": 1}, {"source": 3, "target": 13, "weight": 4}, {"source": 3, "target": 14, "weight": 2}, {"source": 3, "target": 15, "weight": 3}, {"source": 3, "target": 16, "weight": 4}, {"source": 3, "target": 18, "weight": 4}, {"source": 3, "target": 19, "weight": 1}, {"source": 3, "target": 20, "weight": 4}, {"source": 3, "target": 21, "weight": 4}, {"source": 3, "target": 22, "weight": 3}, {"source": 3, "target": 23, "weight": 4}, {"source": 3, "target": 24, "weight": 3}, {"source": 3, "target": 25, "weight": 4}, {"source": 3, "target": 26, "weight": 3}, {"source": 3, "target": 27, "weight": 3}, {"source": 3, "target": 28, "weight": 3}, {"source": 3, "target": 29, "weight": 1}, {"source": 3, "target": 30, "weight": 4}, {"source": 3, "target": 31, "weight": 3}, {"source": 4, "target": 5, "weight": 4}, {"source": 4, "target": 6, "weight": 3}, {"source": 4, "target": 7, "weight": 4}, {"source": 4, "target": 9, "weight": 3}, {"source": 4, "target": 12, "weight": 2}, {"source": 4, "target": 13, "weight": 4}, {"source": 4, "target": 15, "weight": 4}, {"source": 4, "target": 16, "weight": 4}, {"source": 4, "target": 18, "weight": 4}, {"source": 4, "target": 21, "weight": 4}, {"source": 4, "target": 23, "weight": 4}, {"source": 4, "target": 24, "weight": 3}, {"source": 4, "target": 26, "weight": 3}, {"source": 4, "target": 28, "weight": 4}, {"source": 4, "target": 30, "weight": 4}, {"source": 4, "target": 14, "weight": 2}, {"source": 4, "target": 19, "weight": 2}, {"source": 4, "target": 20, "weight": 4}, {"source": 4, "target": 22, "weight": 2}, {"source": 4, "target": 29, "weight": 3}, {"source": 4, "target": 31, "weight": 3}, {"source": 6, "target": 5, "weight": 4}, {"source": 6, "target": 7, "weight": 4}, {"source": 6, "target": 9, "weight": 2}, {"source": 6, "target": 10, "weight": 4}, {"source": 6, "target": 11, "weight": 5}, {"source": 6, "target": 12, "weight": 3}, {"source": 6, "target": 13, "weight": 3}, {"source": 6, "target": 14, "weight": 3}, {"source": 6, "target": 15, "weight": 3}, {"source": 6, "target": 16, "weight": 4}, {"source": 6, "target": 19, "weight": 4}, {"source": 6, "target": 20, "weight": 3}, {"source": 6, "target": 21, "weight": 4}, {"source": 6, "target": 22, "weight": 3}, {"source": 6, "target": 23, "weight": 3}, {"source": 6, "target": 24, "weight": 4}, {"source": 6, "target": 25, "weight": 4}, {"source": 6, "target": 26, "weight": 4}, {"source": 6, "target": 29, "weight": 3}, {"source": 6, "target": 30, "weight": 4}, {"source": 6, "target": 31, "weight": 4}, {"source": 6, "target": 8, "weight": 4}, {"source": 6, "target": 28, "weight": 4}, {"source": 7, "target": 9, "weight": 3}, {"source": 7, "target": 12, "weight": 4}, {"source": 7, "target": 13, "weight": 4}, {"source": 7, "target": 14, "weight": 3}, {"source": 7, "target": 15, "weight": 4}, {"source": 7, "target": 16, "weight": 2}, {"source": 7, "target": 18, "weight": 4}, {"source": 7, "target": 19, "weight": 4}, {"source": 7, "target": 20, "weight": 4}, {"source": 7, "target": 21, "weight": 2}, {"source": 7, "target": 22, "weight": 4}, {"source": 7, "target": 23, "weight": 4}, {"source": 7, "target": 24, "weight": 4}, {"source": 7, "target": 25, "weight": 4}, {"source": 7, "target": 26, "weight": 4}, {"source": 7, "target": 27, "weight": 4}, {"source": 7, "target": 29, "weight": 4}, {"source": 7, "target": 30, "weight": 2}, {"source": 7, "target": 31, "weight": 4}, {"source": 7, "target": 28, "weight": 4}, {"source": 9, "target": 5, "weight": 4}, {"source": 9, "target": 8, "weight": 4}, {"source": 9, "target": 11, "weight": 4}, {"source": 9, "target": 12, "weight": 4}, {"source": 9, "target": 13, "weight": 4}, {"source": 9, "target": 14, "weight": 3}, {"source": 9, "target": 15, "weight": 3}, {"source": 9, "target": 16, "weight": 2}, {"source": 9, "target": 19, "weight": 3}, {"source": 9, "target": 20, "weight": 4}, {"source": 9, "target": 21, "weight": 2}, {"source": 9, "target": 22, "weight": 3}, {"source": 9, "target": 23, "weight": 3}, {"source": 9, "target": 24, "weight": 4}, {"source": 9, "target": 25, "weight": 4}, {"source": 9, "target": 26, "weight": 4}, {"source": 9, "target": 27, "weight": 4}, {"source": 9, "target": 28, "weight": 4}, {"source": 9, "target": 29, "weight": 3}, {"source": 9, "target": 30, "weight": 2}, {"source": 9, "target": 31, "weight": 4}, {"source": 11, "target": 5, "weight": 4}, {"source": 11, "target": 8, "weight": 4}, {"source": 11, "target": 13, "weight": 3}, {"source": 11, "target": 18, "weight": 4}, {"source": 11, "target": 20, "weight": 3}, {"source": 11, "target": 22, "weight": 3}, {"source": 11, "target": 23, "weight": 4}, {"source": 11, "target": 25, "weight": 2}, {"source": 11, "target": 26, "weight": 4}, {"source": 11, "target": 27, "weight": 4}, {"source": 11, "target": 12, "weight": 4}, {"source": 11, "target": 14, "weight": 4}, {"source": 11, "target": 15, "weight": 4}, {"source": 11, "target": 16, "weight": 5}, {"source": 11, "target": 19, "weight": 4}, {"source": 11, "target": 21, "weight": 4}, {"source": 11, "target": 28, "weight": 4}, {"source": 11, "target": 29, "weight": 4}, {"source": 11, "target": 31, "weight": 4}, {"source": 12, "target": 5, "weight": 4}, {"source": 12, "target": 13, "weight": 4}, {"source": 12, "target": 14, "weight": 2}, {"source": 12, "target": 15, "weight": 3}, {"source": 12, "target": 16, "weight": 3}, {"source": 12, "target": 18, "weight": 4}, {"source": 12, "target": 19, "weight": 1}, {"source": 12, "target": 20, "weight": 4}, {"source": 12, "target": 21, "weight": 4}, {"source": 12, "target": 22, "weight": 3}, {"source": 12, "target": 23, "weight": 4}, {"source": 12, "target": 24, "weight": 3}, {"source": 12, "target": 25, "weight": 4}, {"source": 12, "target": 26, "weight": 3}, {"source": 12, "target": 27, "weight": 4}, {"source": 12, "target": 28, "weight": 4}, {"source": 12, "target": 29, "weight": 1}, {"source": 12, "target": 30, "weight": 4}, {"source": 12, "target": 31, "weight": 3}, {"source": 13, "target": 5, "weight": 4}, {"source": 13, "target": 15, "weight": 4}, {"source": 13, "target": 16, "weight": 3}, {"source": 13, "target": 18, "weight": 4}, {"source": 13, "target": 19, "weight": 4}, {"source": 13, "target": 20, "weight": 2}, {"source": 13, "target": 21, "weight": 4}, {"source": 13, "target": 23, "weight": 4}, {"source": 13, "target": 25, "weight": 2}, {"source": 13, "target": 26, "weight": 4}, {"source": 13, "target": 27, "weight": 4}, {"source": 13, "target": 28, "weight": 4}, {"source": 13, "target": 29, "weight": 3}, {"source": 13, "target": 14, "weight": 4}, {"source": 13, "target": 22, "weight": 4}, {"source": 13, "target": 24, "weight": 4}, {"source": 13, "target": 30, "weight": 4}, {"source": 13, "target": 31, "weight": 4}, {"source": 14, "target": 5, "weight": 2}, {"source": 14, "target": 8, "weight": 4}, {"source": 14, "target": 10, "weight": 4}, {"source": 14, "target": 15, "weight": 4}, {"source": 14, "target": 16, "weight": 4}, {"source": 14, "target": 18, "weight": 3}, {"source": 14, "target": 19, "weight": 1}, {"source": 14, "target": 20, "weight": 4}, {"source": 14, "target": 21, "weight": 3}, {"source": 14, "target": 22, "weight": 3}, {"source": 14, "target": 23, "weight": 4}, {"source": 14, "target": 24, "weight": 2}, {"source": 14, "target": 25, "weight": 4}, {"source": 14, "target": 26, "weight": 4}, {"source": 14, "target": 27, "weight": 4}, {"source": 14, "target": 28, "weight": 3}, {"source": 14, "target": 29, "weight": 3}, {"source": 14, "target": 30, "weight": 4}, {"source": 14, "target": 31, "weight": 3}, {"source": 15, "target": 5, "weight": 4}, {"source": 15, "target": 8, "weight": 4}, {"source": 15, "target": 10, "weight": 4}, {"source": 15, "target": 16, "weight": 4}, {"source": 15, "target": 18, "weight": 4}, {"source": 15, "target": 19, "weight": 4}, {"source": 15, "target": 20, "weight": 4}, {"source": 15, "target": 21, "weight": 4}, {"source": 15, "target": 22, "weight": 4}, {"source": 15, "target": 24, "weight": 4}, {"source": 15, "target": 25, "weight": 4}, {"source": 15, "target": 26, "weight": 4}, {"source": 15, "target": 27, "weight": 4}, {"source": 15, "target": 28, "weight": 4}, {"source": 15, "target": 29, "weight": 3}, {"source": 15, "target": 30, "weight": 4}, {"source": 15, "target": 31, "weight": 4}, {"source": 16, "target": 5, "weight": 4}, {"source": 16, "target": 18, "weight": 4}, {"source": 16, "target": 19, "weight": 4}, {"source": 16, "target": 20, "weight": 4}, {"source": 16, "target": 21, "weight": 2}, {"source": 16, "target": 22, "weight": 4}, {"source": 16, "target": 23, "weight": 4}, {"source": 16, "target": 25, "weight": 4}, {"source": 16, "target": 26, "weight": 4}, {"source": 16, "target": 27, "weight": 4}, {"source": 16, "target": 29, "weight": 4}, {"source": 16, "target": 30, "weight": 2}, {"source": 16, "target": 24, "weight": 4}, {"source": 19, "target": 5, "weight": 4}, {"source": 19, "target": 18, "weight": 3}, {"source": 19, "target": 20, "weight": 4}, {"source": 19, "target": 22, "weight": 3}, {"source": 19, "target": 23, "weight": 4}, {"source": 19, "target": 24, "weight": 3}, {"source": 19, "target": 25, "weight": 4}, {"source": 19, "target": 26, "weight": 2}, {"source": 19, "target": 27, "weight": 3}, {"source": 19, "target": 28, "weight": 2}, {"source": 19, "target": 29, "weight": 1}, {"source": 19, "target": 30, "weight": 4}, {"source": 19, "target": 31, "weight": 3}, {"source": 19, "target": 21, "weight": 4}, {"source": 20, "target": 8, "weight": 3}, {"source": 20, "target": 10, "weight": 4}, {"source": 20, "target": 18, "weight": 4}, {"source": 20, "target": 21, "weight": 4}, {"source": 20, "target": 22, "weight": 4}, {"source": 20, "target": 23, "weight": 4}, {"source": 20, "target": 25, "weight": 2}, {"source": 20, "target": 26, "weight": 3}, {"source": 20, "target": 27, "weight": 4}, {"source": 20, "target": 28, "weight": 4}, {"source": 20, "target": 29, "weight": 4}, {"source": 20, "target": 30, "weight": 4}, {"source": 20, "target": 31, "weight": 4}, {"source": 21, "target": 8, "weight": 4}, {"source": 21, "target": 18, "weight": 4}, {"source": 21, "target": 5, "weight": 4}, {"source": 21, "target": 10, "weight": 3}, {"source": 21, "target": 22, "weight": 4}, {"source": 21, "target": 23, "weight": 4}, {"source": 21, "target": 25, "weight": 3}, {"source": 21, "target": 26, "weight": 4}, {"source": 21, "target": 27, "weight": 4}, {"source": 21, "target": 28, "weight": 3}, {"source": 21, "target": 29, "weight": 4}, {"source": 21, "target": 30, "weight": 2}, {"source": 21, "target": 31, "weight": 4}, {"source": 22, "target": 5, "weight": 3}, {"source": 22, "target": 8, "weight": 4}, {"source": 22, "target": 10, "weight": 3}, {"source": 22, "target": 17, "weight": 4}, {"source": 22, "target": 18, "weight": 3}, {"source": 22, "target": 23, "weight": 3}, {"source": 22, "target": 24, "weight": 4}, {"source": 22, "target": 25, "weight": 3}, {"source": 22, "target": 26, "weight": 3}, {"source": 22, "target": 27, "weight": 4}, {"source": 22, "target": 28, "weight": 4}, {"source": 22, "target": 29, "weight": 4}, {"source": 22, "target": 30, "weight": 4}, {"source": 22, "target": 31, "weight": 3}, {"source": 23, "target": 5, "weight": 4}, {"source": 23, "target": 18, "weight": 4}, {"source": 23, "target": 25, "weight": 4}, {"source": 23, "target": 26, "weight": 3}, {"source": 23, "target": 27, "weight": 4}, {"source": 23, "target": 29, "weight": 4}, {"source": 23, "target": 31, "weight": 4}, {"source": 23, "target": 24, "weight": 4}, {"source": 23, "target": 28, "weight": 3}, {"source": 23, "target": 30, "weight": 4}, {"source": 24, "target": 26, "weight": 3}, {"source": 24, "target": 29, "weight": 2}, {"source": 24, "target": 31, "weight": 2}, {"source": 25, "target": 18, "weight": 4}, {"source": 25, "target": 26, "weight": 4}, {"source": 25, "target": 27, "weight": 4}, {"source": 25, "target": 28, "weight": 4}, {"source": 25, "target": 29, "weight": 4}, {"source": 25, "target": 31, "weight": 4}, {"source": 25, "target": 30, "weight": 4}, {"source": 26, "target": 5, "weight": 2}, {"source": 26, "target": 18, "weight": 1}, {"source": 26, "target": 8, "weight": 4}, {"source": 26, "target": 10, "weight": 4}, {"source": 26, "target": 17, "weight": 4}, {"source": 26, "target": 27, "weight": 2}, {"source": 26, "target": 28, "weight": 1}, {"source": 26, "target": 29, "weight": 2}, {"source": 26, "target": 30, "weight": 4}, {"source": 26, "target": 31, "weight": 3}, {"source": 27, "target": 5, "weight": 3}, {"source": 27, "target": 18, "weight": 3}, {"source": 27, "target": 10, "weight": 4}, {"source": 27, "target": 28, "weight": 1}, {"source": 27, "target": 29, "weight": 3}, {"source": 27, "target": 31, "weight": 4}, {"source": 27, "target": 30, "weight": 5}, {"source": 28, "target": 5, "weight": 2}, {"source": 28, "target": 18, "weight": 2}, {"source": 28, "target": 10, "weight": 4}, {"source": 28, "target": 29, "weight": 3}, {"source": 28, "target": 30, "weight": 4}, {"source": 28, "target": 31, "weight": 4}, {"source": 29, "target": 5, "weight": 4}, {"source": 29, "target": 18, "weight": 3}, {"source": 29, "target": 8, "weight": 4}, {"source": 29, "target": 30, "weight": 4}, {"source": 29, "target": 31, "weight": 3}, {"source": 30, "target": 5, "weight": 4}, {"source": 30, "target": 31, "weight": 4}, {"source": 31, "target": 5, "weight": 4}, {"source": 31, "target": 8, "weight": 4}, {"source": 31, "target": 18, "weight": 2}, {"source": 31, "target": 10, "weight": 4}, {"source": 5, "target": 18, "weight": 4}, {"source": 10, "target": 8, "weight": 4}]}