{"nodes": [{"id": 1, "x": 122.52546366256486, "y": 40.343320458020145, "group": 0}, {"id": 2, "x": 121.2129467362043, "y": 40.39379462261511, "group": 0}, {"id": 3, "x": 120.98156045936534, "y": 41.5580869558534, "group": 0}, {"id": 4, "x": 122.00048840512875, "y": 39.654290305601386, "group": 0}, {"id": 5, "x": 123.07179003043774, "y": 38.65248221903182, "group": 0}, {"id": 6, "x": 123.25556446297995, "y": 39.9603872658473, "group": 0}, {"id": 7, "x": 122.81472761696018, "y": 41.258175286065025, "group": 0}, {"id": 8, "x": 121.72995906929046, "y": 39.70079925395811, "group": 0}, {"id": 9, "x": 123.18271643731946, "y": 39.887592657031895, "group": 0}, {"id": 10, "x": 122.10773942420404, "y": 40.721620648169825, "group": 0}, {"id": 11, "x": 120.57404206019689, "y": 39.961148089213154, "group": 0}, {"id": 12, "x": 121.63784839611768, "y": 40.898663839584984, "group": 0}, {"id": 13, "x": 122.79049846993425, "y": 41.59860782967151, "group": 0}, {"id": 14, "x": 123.48966500350723, "y": 40.835066686089824, "group": 0}, {"id": 15, "x": 121.67313412623028, "y": 39.04789475574659, "group": 0}, {"id": 16, "x": 122.18614000822421, "y": 39.7923327274773, "group": 0}, {"id": 17, "x": 121.93153747945264, "y": 40.718131872272195, "group": 0}, {"id": 18, "x": 122.89255567706479, "y": 39.77114462447518, "group": 0}, {"id": 19, "x": 122.24081849701501, "y": 40.203724076377945, "group": 0}, {"id": 20, "x": 121.5380343453463, "y": 39.66409574940788, "group": 0}, {"id": 21, "x": 123.34727558046418, "y": 39.77254622195054, "group": 0}, {"id": 22, "x": 123.28309773501667, "y": 39.224684938121015, "group": 0}, {"id": 23, "x": 122.04817144412908, "y": 38.95525659728793, "group": 0}, {"id": 24, "x": 123.0352631409558, "y": 39.667957728589016, "group": 0}, {"id": 25, "x": 122.7495811070652, "y": 39.81256675448136, "group": 0}], "links": [{"source": 1, "target": 23, "weight": 1.046242775}, {"source": 1, "target": 5, "weight": 0.523121387}, {"source": 1, "target": 9, "weight": 0.261560694}, {"source": 1, "target": 14, "weight": 0.261560694}, {"source": 1, "target": 10, "weight": 3.661849711}, {"source": 1, "target": 11, "weight": 0.523121387}, {"source": 1, "target": 4, "weight": 0.523121387}, {"source": 1, "target": 6, "weight": 0.261560694}, {"source": 1, "target": 12, "weight": 0.784682081}, {"source": 1, "target": 15, "weight": 1.307803468}, {"source": 1, "target": 2, "weight": 0.261560694}, {"source": 1, "target": 13, "weight": 1.046242775}, {"source": 1, "target": 18, "weight": 1.307803468}, {"source": 1, "target": 16, "weight": 0.261560694}, {"source": 1, "target": 21, "weight": 0.784682081}, {"source": 1, "target": 17, "weight": 0.784682081}, {"source": 2, "target": 19, "weight": 2.092485549}, {"source": 2, "target": 23, "weight": 0.261560694}, {"source": 2, "target": 5, "weight": 1.046242775}, {"source": 2, "target": 14, "weight": 0.523121387}, {"source": 2, "target": 10, "weight": 4.184971098}, {"source": 2, "target": 11, "weight": 0.261560694}, {"source": 2, "target": 4, "weight": 0.784682081}, {"source": 2, "target": 12, "weight": 0.523121387}, {"source": 2, "target": 8, "weight": 0.261560694}, {"source": 2, "target": 13, "weight": 1.046242775}, {"source": 2, "target": 7, "weight": 0.523121387}, {"source": 2, "target": 20, "weight": 0.523121387}, {"source": 2, "target": 17, "weight": 0.523121387}, {"source": 2, "target": 18, "weight": 1.307803468}, {"source": 3, "target": 24, "weight": 0.261560694}, {"source": 3, "target": 9, "weight": 0.261560694}, {"source": 3, "target": 10, "weight": 0.784682081}, {"source": 3, "target": 11, "weight": 0.261560694}, {"source": 3, "target": 8, "weight": 0.261560694}, {"source": 3, "target": 18, "weight": 0.261560694}, {"source": 3, "target": 6, "weight": 0.261560694}, {"source": 3, "target": 12, "weight": 0.261560694}, {"source": 3, "target": 15, "weight": 0.523121387}, {"source": 4, "target": 23, "weight": 0.261560694}, {"source": 4, "target": 25, "weight": 1.569364162}, {"source": 4, "target": 5, "weight": 0.784682081}, {"source": 4, "target": 9, "weight": 0.261560694}, {"source": 4, "target": 14, "weight": 0.523121387}, {"source": 4, "target": 10, "weight": 0.261560694}, {"source": 4, "target": 11, "weight": 0.523121387}, {"source": 4, "target": 8, "weight": 1.307803468}, {"source": 4, "target": 18, "weight": 0.523121387}, {"source": 4, "target": 15, "weight": 1.307803468}, {"source": 5, "target": 8, "weight": 3.138728324}, {"source": 5, "target": 13, "weight": 1.046242775}, {"source": 5, "target": 18, "weight": 0.261560694}, {"source": 5, "target": 7, "weight": 0.784682081}, {"source": 5, "target": 16, "weight": 0.261560694}, {"source": 5, "target": 20, "weight": 0.261560694}, {"source": 5, "target": 17, "weight": 0.523121387}, {"source": 5, "target": 10, "weight": 0.784682081}, {"source": 5, "target": 11, "weight": 0.261560694}, {"source": 5, "target": 6, "weight": 0.523121387}, {"source": 5, "target": 12, "weight": 0.261560694}, {"source": 6, "target": 22, "weight": 1.830924855}, {"source": 6, "target": 23, "weight": 0.261560694}, {"source": 6, "target": 25, "weight": 0.784682081}, {"source": 6, "target": 14, "weight": 0.523121387}, {"source": 6, "target": 11, "weight": 1.307803468}, {"source": 6, "target": 18, "weight": 0.523121387}, {"source": 6, "target": 16, "weight": 1.307803468}, {"source": 6, "target": 17, "weight": 0.261560694}, {"source": 6, "target": 20, "weight": 0.261560694}, {"source": 6, "target": 15, "weight": 0.523121387}, {"source": 7, "target": 22, "weight": 0.784682081}, {"source": 7, "target": 19, "weight": 3.138728324}, {"source": 7, "target": 24, "weight": 0.523121387}, {"source": 7, "target": 23, "weight": 2.092485549}, {"source": 7, "target": 25, "weight": 0.784682081}, {"source": 7, "target": 9, "weight": 1.046242775}, {"source": 7, "target": 10, "weight": 0.261560694}, {"source": 7, "target": 8, "weight": 3.661849711}, {"source": 7, "target": 13, "weight": 0.523121387}, {"source": 7, "target": 18, "weight": 0.523121387}, {"source": 7, "target": 21, "weight": 2.092485549}, {"source": 7, "target": 17, "weight": 0.523121387}, {"source": 7, "target": 20, "weight": 7.323699422}, {"source": 7, "target": 16, "weight": 0.784682081}, {"source": 8, "target": 22, "weight": 0.523121387}, {"source": 8, "target": 19, "weight": 1.307803468}, {"source": 8, "target": 24, "weight": 0.523121387}, {"source": 8, "target": 23, "weight": 3.400289017}, {"source": 8, "target": 25, "weight": 0.784682081}, {"source": 8, "target": 10, "weight": 1.046242775}, {"source": 8, "target": 11, "weight": 1.046242775}, {"source": 8, "target": 12, "weight": 0.261560694}, {"source": 8, "target": 15, "weight": 2.354046243}, {"source": 8, "target": 17, "weight": 0.523121387}, {"source": 8, "target": 20, "weight": 5.492774566}, {"source": 8, "target": 18, "weight": 0.261560694}, {"source": 8, "target": 16, "weight": 0.523121387}, {"source": 9, "target": 24, "weight": 7.585260116}, {"source": 9, "target": 23, "weight": 0.523121387}, {"source": 9, "target": 13, "weight": 0.523121387}, {"source": 9, "target": 21, "weight": 0.523121387}, {"source": 9, "target": 15, "weight": 0.261560694}, {"source": 10, "target": 19, "weight": 0.261560694}, {"source": 10, "target": 24, "weight": 0.261560694}, {"source": 10, "target": 23, "weight": 0.523121387}, {"source": 10, "target": 25, "weight": 1.046242775}, {"source": 10, "target": 13, "weight": 0.523121387}, {"source": 10, "target": 21, "weight": 1.307803468}, {"source": 10, "target": 17, "weight": 0.261560694}, {"source": 10, "target": 20, "weight": 0.523121387}, {"source": 10, "target": 12, "weight": 0.523121387}, {"source": 11, "target": 14, "weight": 0.261560694}, {"source": 11, "target": 18, "weight": 0.261560694}, {"source": 11, "target": 16, "weight": 0.261560694}, {"source": 11, "target": 20, "weight": 0.261560694}, {"source": 11, "target": 12, "weight": 0.261560694}, {"source": 12, "target": 22, "weight": 0.261560694}, {"source": 12, "target": 19, "weight": 0.784682081}, {"source": 12, "target": 24, "weight": 0.261560694}, {"source": 12, "target": 23, "weight": 0.523121387}, {"source": 12, "target": 14, "weight": 0.523121387}, {"source": 12, "target": 13, "weight": 1.307803468}, {"source": 12, "target": 21, "weight": 0.261560694}, {"source": 12, "target": 17, "weight": 0.523121387}, {"source": 12, "target": 18, "weight": 2.354046243}, {"source": 12, "target": 16, "weight": 0.261560694}, {"source": 13, "target": 24, "weight": 0.523121387}, {"source": 13, "target": 23, "weight": 0.261560694}, {"source": 13, "target": 25, "weight": 0.261560694}, {"source": 13, "target": 15, "weight": 1.569364162}, {"source": 13, "target": 21, "weight": 0.784682081}, {"source": 13, "target": 17, "weight": 0.261560694}, {"source": 14, "target": 19, "weight": 1.046242775}, {"source": 14, "target": 24, "weight": 0.784682081}, {"source": 14, "target": 23, "weight": 0.523121387}, {"source": 14, "target": 25, "weight": 0.523121387}, {"source": 14, "target": 21, "weight": 2.87716763}, {"source": 14, "target": 15, "weight": 0.523121387}, {"source": 15, "target": 22, "weight": 0.784682081}, {"source": 15, "target": 19, "weight": 1.046242775}, {"source": 15, "target": 23, "weight": 0.523121387}, {"source": 15, "target": 16, "weight": 0.523121387}, {"source": 15, "target": 20, "weight": 0.784682081}, {"source": 15, "target": 18, "weight": 1.830924855}, {"source": 16, "target": 22, "weight": 1.569364162}, {"source": 16, "target": 19, "weight": 0.523121387}, {"source": 16, "target": 24, "weight": 0.261560694}, {"source": 16, "target": 23, "weight": 0.523121387}, {"source": 16, "target": 25, "weight": 2.092485549}, {"source": 16, "target": 18, "weight": 0.784682081}, {"source": 16, "target": 21, "weight": 0.784682081}, {"source": 16, "target": 20, "weight": 0.261560694}, {"source": 17, "target": 22, "weight": 0.523121387}, {"source": 17, "target": 25, "weight": 0.261560694}, {"source": 17, "target": 18, "weight": 0.523121387}, {"source": 17, "target": 20, "weight": 2.354046243}, {"source": 17, "target": 21, "weight": 0.261560694}, {"source": 18, "target": 22, "weight": 0.261560694}, {"source": 18, "target": 19, "weight": 0.523121387}, {"source": 18, "target": 23, "weight": 0.523121387}, {"source": 18, "target": 21, "weight": 0.784682081}, {"source": 18, "target": 20, "weight": 1.046242775}, {"source": 19, "target": 22, "weight": 2.092485549}, {"source": 19, "target": 20, "weight": 1.569364162}, {"source": 19, "target": 21, "weight": 1.830924855}, {"source": 19, "target": 25, "weight": 0.523121387}, {"source": 19, "target": 23, "weight": 2.354046243}, {"source": 19, "target": 24, "weight": 0.523121387}, {"source": 20, "target": 22, "weight": 2.092485549}, {"source": 20, "target": 24, "weight": 0.523121387}, {"source": 20, "target": 23, "weight": 1.569364162}, {"source": 20, "target": 21, "weight": 1.046242775}, {"source": 21, "target": 22, "weight": 0.784682081}, {"source": 21, "target": 24, "weight": 1.830924855}, {"source": 21, "target": 25, "weight": 2.092485549}, {"source": 22, "target": 23, "weight": 2.354046243}, {"source": 22, "target": 24, "weight": 1.307803468}, {"source": 22, "target": 25, "weight": 5.492774566}, {"source": 23, "target": 24, "weight": 0.523121387}, {"source": 23, "target": 25, "weight": 3.400289017}, {"source": 24, "target": 25, "weight": 1.046242775}]}