{"nodes": [{"id": 1, "x": -0.9669472238481326, "y": -0.02535758675469197, "group": 0}, {"id": 2, "x": -0.7135730682528065, "y": -0.12989871235896888, "group": 0}, {"id": 3, "x": -0.8178040993062312, "y": 0.10861096946291862, "group": 0}, {"id": 4, "x": -0.8360586596438314, "y": -0.10092719679012235, "group": 0}, {"id": 5, "x": -1.089305604012222, "y": -0.1772396828032948, "group": 0}, {"id": 6, "x": -0.971082666792095, "y": -0.15429879597196805, "group": 0}, {"id": 7, "x": -0.7050343716585468, "y": -0.005503792137441428, "group": 0}, {"id": 8, "x": -0.9777343734469858, "y": 0.09408899569925208, "group": 0}, {"id": 9, "x": -0.8317739107309794, "y": -0.23351320436022946, "group": 0}, {"id": 10, "x": -0.6908662857035586, "y": 0.10152832628865906, "group": 0}, {"id": 11, "x": -0.7137027197765591, "y": -0.29897735404224646, "group": 0}, {"id": 12, "x": -0.6104608935968205, "y": -0.11912591968422871, "group": 0}, {"id": 13, "x": -1.080144902245179, "y": -0.022217323801587075, "group": 0}, {"id": 14, "x": -0.9030335356031766, "y": -0.3327357955384169, "group": 0}, {"id": 15, "x": -0.787538085812701, "y": -0.38460136026481095, "group": 0}, {"id": 16, "x": -0.6038540252232271, "y": -0.24089771511645766, "group": 0}, {"id": 17, "x": -1.0018158230851129, "y": -0.2767338346835247, "group": 0}], "links": [{"source": 1, "target": 2, "weight": 6}, {"source": 1, "target": 3, "weight": 8}, {"source": 1, "target": 4, "weight": 11}, {"source": 1, "target": 5, "weight": 5}, {"source": 1, "target": 6, "weight": 1}, {"source": 1, "target": 7, "weight": 7}, {"source": 1, "target": 8, "weight": 1}, {"source": 1, "target": 9, "weight": 11}, {"source": 1, "target": 10, "weight": 5}, {"source": 1, "target": 11, "weight": 13}, {"source": 1, "target": 12, "weight": 11}, {"source": 1, "target": 13, "weight": 1}, {"source": 1, "target": 14, "weight": 4}, {"source": 1, "target": 15, "weight": 11}, {"source": 1, "target": 16, "weight": 13}, {"source": 1, "target": 17, "weight": 3}, {"source": 2, "target": 3, "weight": 7}, {"source": 2, "target": 4, "weight": 3}, {"source": 2, "target": 5, "weight": 8}, {"source": 2, "target": 6, "weight": 11}, {"source": 2, "target": 7, "weight": 11}, {"source": 2, "target": 8, "weight": 9}, {"source": 2, "target": 9, "weight": 9}, {"source": 2, "target": 10, "weight": 11}, {"source": 2, "target": 11, "weight": 3}, {"source": 2, "target": 12, "weight": 2}, {"source": 2, "target": 13, "weight": 11}, {"source": 2, "target": 14, "weight": 10}, {"source": 2, "target": 15, "weight": 15}, {"source": 2, "target": 16, "weight": 5}, {"source": 2, "target": 17, "weight": 6}, {"source": 3, "target": 4, "weight": 16}, {"source": 3, "target": 5, "weight": 14}, {"source": 3, "target": 6, "weight": 14}, {"source": 3, "target": 7, "weight": 6}, {"source": 3, "target": 8, "weight": 15}, {"source": 3, "target": 9, "weight": 14}, {"source": 3, "target": 10, "weight": 15}, {"source": 3, "target": 11, "weight": 5}, {"source": 3, "target": 12, "weight": 9}, {"source": 3, "target": 13, "weight": 15}, {"source": 3, "target": 14, "weight": 13}, {"source": 3, "target": 15, "weight": 7}, {"source": 3, "target": 16, "weight": 15}, {"source": 3, "target": 17, "weight": 9}, {"source": 4, "target": 5, "weight": 4}, {"source": 4, "target": 6, "weight": 5}, {"source": 4, "target": 7, "weight": 5}, {"source": 4, "target": 8, "weight": 4}, {"source": 4, "target": 9, "weight": 4}, {"source": 4, "target": 10, "weight": 10}, {"source": 4, "target": 11, "weight": 8}, {"source": 4, "target": 12, "weight": 6}, {"source": 4, "target": 13, "weight": 12}, {"source": 4, "target": 14, "weight": 11}, {"source": 4, "target": 15, "weight": 4}, {"source": 4, "target": 16, "weight": 3}, {"source": 4, "target": 17, "weight": 4}, {"source": 5, "target": 6, "weight": 7}, {"source": 5, "target": 7, "weight": 8}, {"source": 5, "target": 8, "weight": 5}, {"source": 5, "target": 9, "weight": 5}, {"source": 5, "target": 10, "weight": 12}, {"source": 5, "target": 11, "weight": 7}, {"source": 5, "target": 12, "weight": 10}, {"source": 5, "target": 13, "weight": 5}, {"source": 5, "target": 14, "weight": 12}, {"source": 5, "target": 15, "weight": 13}, {"source": 5, "target": 16, "weight": 12}, {"source": 5, "target": 17, "weight": 2}, {"source": 6, "target": 7, "weight": 13}, {"source": 6, "target": 8, "weight": 6}, {"source": 6, "target": 9, "weight": 1}, {"source": 6, "target": 10, "weight": 7}, {"source": 6, "target": 11, "weight": 10}, {"source": 6, "target": 12, "weight": 15}, {"source": 6, "target": 13, "weight": 3}, {"source": 6, "target": 14, "weight": 2}, {"source": 6, "target": 15, "weight": 9}, {"source": 6, "target": 16, "weight": 11}, {"source": 6, "target": 17, "weight": 12}, {"source": 7, "target": 8, "weight": 13}, {"source": 7, "target": 9, "weight": 8}, {"source": 7, "target": 10, "weight": 2}, {"source": 7, "target": 11, "weight": 9}, {"source": 7, "target": 12, "weight": 1}, {"source": 7, "target": 13, "weight": 6}, {"source": 7, "target": 14, "weight": 5}, {"source": 7, "target": 15, "weight": 16}, {"source": 7, "target": 16, "weight": 7}, {"source": 7, "target": 17, "weight": 11}, {"source": 8, "target": 9, "weight": 12}, {"source": 8, "target": 10, "weight": 8}, {"source": 8, "target": 11, "weight": 11}, {"source": 8, "target": 12, "weight": 12}, {"source": 8, "target": 13, "weight": 2}, {"source": 8, "target": 14, "weight": 14}, {"source": 8, "target": 15, "weight": 14}, {"source": 8, "target": 16, "weight": 10}, {"source": 8, "target": 17, "weight": 10}, {"source": 9, "target": 10, "weight": 3}, {"source": 9, "target": 11, "weight": 4}, {"source": 9, "target": 12, "weight": 3}, {"source": 9, "target": 13, "weight": 8}, {"source": 9, "target": 14, "weight": 1}, {"source": 9, "target": 15, "weight": 1}, {"source": 9, "target": 16, "weight": 2}, {"source": 9, "target": 17, "weight": 1}, {"source": 10, "target": 11, "weight": 16}, {"source": 10, "target": 12, "weight": 16}, {"source": 10, "target": 13, "weight": 13}, {"source": 10, "target": 14, "weight": 15}, {"source": 10, "target": 15, "weight": 12}, {"source": 10, "target": 16, "weight": 16}, {"source": 10, "target": 17, "weight": 16}, {"source": 11, "target": 12, "weight": 5}, {"source": 11, "target": 13, "weight": 14}, {"source": 11, "target": 14, "weight": 3}, {"source": 11, "target": 15, "weight": 5}, {"source": 11, "target": 16, "weight": 9}, {"source": 11, "target": 17, "weight": 5}, {"source": 12, "target": 13, "weight": 9}, {"source": 12, "target": 14, "weight": 6}, {"source": 12, "target": 15, "weight": 6}, {"source": 12, "target": 16, "weight": 1}, {"source": 12, "target": 17, "weight": 7}, {"source": 13, "target": 14, "weight": 7}, {"source": 13, "target": 15, "weight": 10}, {"source": 13, "target": 16, "weight": 14}, {"source": 13, "target": 17, "weight": 8}, {"source": 14, "target": 15, "weight": 8}, {"source": 14, "target": 16, "weight": 8}, {"source": 14, "target": 17, "weight": 14}, {"source": 15, "target": 16, "weight": 6}, {"source": 15, "target": 17, "weight": 13}, {"source": 16, "target": 17, "weight": 15}]}