{"nodes": [{"id": 1, "x": 0.19836047633850848, "y": 0.022160708912726392, "group": 0}, {"id": 2, "x": 0.18404623123489003, "y": -0.03557787067696981, "group": 0}, {"id": 3, "x": 0.2566314800427111, "y": -0.10235997585524262, "group": 0}, {"id": 4, "x": 0.17583385643637808, "y": 0.010141517076469759, "group": 0}, {"id": 5, "x": 0.3606187817135016, "y": 0.012934827323673308, "group": 0}, {"id": 6, "x": 0.17011448465882462, "y": -0.08810193896471641, "group": 0}, {"id": 7, "x": 0.21908916886530472, "y": -0.045962649740031114, "group": 0}, {"id": 8, "x": 0.21717499249543282, "y": 0.010947409004575899, "group": 0}, {"id": 9, "x": 0.14341535512553708, "y": -0.0028575915148111564, "group": 0}, {"id": 10, "x": 0.20145353535067875, "y": -0.07879066426418062, "group": 0}, {"id": 11, "x": 0.212435868610092, "y": 0.08045143207753902, "group": 0}, {"id": 12, "x": 0.24822058015561932, "y": -0.00873273188885136, "group": 0}, {"id": 13, "x": 0.2138244799829574, "y": -0.019354436467776074, "group": 0}, {"id": 14, "x": 0.14835266905687702, "y": -0.06114896046483129, "group": 0}, {"id": 15, "x": 0.19016115968158379, "y": -0.004282169568964161, "group": 0}, {"id": 16, "x": -0.7322905435764279, "y": 0.17157501261255995, "group": 0}, {"id": 17, "x": 0.08798091275053438, "y": 0.9143693740255278, "group": 0}, {"id": 18, "x": 0.2780049076228004, "y": -0.04679998990310823, "group": 0}, {"id": 19, "x": -0.3012722464562566, "y": -1.0, "group": 0}, {"id": 20, "x": -0.5132756581262361, "y": 0.5407124111354725, "group": 0}, {"id": 21, "x": -0.42317854989635917, "y": 0.9104595904389886, "group": 0}, {"id": 22, "x": -0.34870240210984355, "y": -0.18428199577812987, "group": 0}, {"id": 23, "x": -0.3845853083656772, "y": -0.23435867162207957, "group": 0}, {"id": 24, "x": -0.46413486447225744, "y": -0.46829172293220617, "group": 0}, {"id": 25, "x": -0.33827936711917334, "y": -0.2928509129656347, "group": 0}], "links": [{"source": 1, "target": 2, "weight": 1.023364486}, {"source": 1, "target": 8, "weight": 2.6152647975}, {"source": 1, "target": 13, "weight": 0.5685358255}, {"source": 1, "target": 7, "weight": 0.4548286604}, {"source": 1, "target": 9, "weight": 0.5685358255}, {"source": 1, "target": 10, "weight": 0.4548286604}, {"source": 1, "target": 11, "weight": 0.9096573209}, {"source": 1, "target": 4, "weight": 1.1370716511}, {"source": 1, "target": 6, "weight": 0.3411214953}, {"source": 1, "target": 12, "weight": 0.9096573209}, {"source": 1, "target": 15, "weight": 0.9096573209}, {"source": 2, "target": 8, "weight": 1.7056074766}, {"source": 2, "target": 13, "weight": 1.023364486}, {"source": 2, "target": 18, "weight": 0.1137071651}, {"source": 2, "target": 7, "weight": 2.5015576324}, {"source": 2, "target": 9, "weight": 0.1137071651}, {"source": 2, "target": 14, "weight": 0.7959501558}, {"source": 2, "target": 10, "weight": 1.5919003115}, {"source": 2, "target": 4, "weight": 0.6822429907}, {"source": 2, "target": 12, "weight": 0.2274143302}, {"source": 2, "target": 15, "weight": 0.6822429907}, {"source": 3, "target": 18, "weight": 1.3644859813}, {"source": 3, "target": 10, "weight": 1.4781931464}, {"source": 3, "target": 12, "weight": 0.2274143302}, {"source": 3, "target": 4, "weight": 0.1137071651}, {"source": 3, "target": 6, "weight": 0.3411214953}, {"source": 4, "target": 8, "weight": 1.7056074766}, {"source": 4, "target": 13, "weight": 1.023364486}, {"source": 4, "target": 18, "weight": 0.1137071651}, {"source": 4, "target": 5, "weight": 0.1137071651}, {"source": 4, "target": 9, "weight": 5.9127725857}, {"source": 4, "target": 11, "weight": 0.3411214953}, {"source": 4, "target": 6, "weight": 0.2274143302}, {"source": 4, "target": 12, "weight": 0.7959501558}, {"source": 4, "target": 15, "weight": 5.5716510903}, {"source": 5, "target": 8, "weight": 0.1137071651}, {"source": 5, "target": 18, "weight": 0.3411214953}, {"source": 6, "target": 13, "weight": 0.3411214953}, {"source": 6, "target": 18, "weight": 0.1137071651}, {"source": 6, "target": 14, "weight": 2.1604361371}, {"source": 6, "target": 10, "weight": 0.2274143302}, {"source": 6, "target": 12, "weight": 0.1137071651}, {"source": 6, "target": 15, "weight": 0.2274143302}, {"source": 7, "target": 8, "weight": 0.5685358255}, {"source": 7, "target": 13, "weight": 0.6822429907}, {"source": 7, "target": 18, "weight": 0.1137071651}, {"source": 7, "target": 9, "weight": 0.1137071651}, {"source": 7, "target": 10, "weight": 0.6822429907}, {"source": 7, "target": 12, "weight": 0.4548286604}, {"source": 7, "target": 15, "weight": 1.2507788162}, {"source": 8, "target": 13, "weight": 3.0700934579}, {"source": 8, "target": 18, "weight": 0.3411214953}, {"source": 8, "target": 14, "weight": 0.1137071651}, {"source": 8, "target": 11, "weight": 0.7959501558}, {"source": 8, "target": 12, "weight": 0.1137071651}, {"source": 8, "target": 15, "weight": 6.1401869159}, {"source": 9, "target": 14, "weight": 1.9330218069}, {"source": 9, "target": 15, "weight": 3.2975077882}, {"source": 10, "target": 13, "weight": 0.3411214953}, {"source": 10, "target": 18, "weight": 0.2274143302}, {"source": 10, "target": 14, "weight": 2.2741433022}, {"source": 10, "target": 12, "weight": 0.1137071651}, {"source": 10, "target": 15, "weight": 0.2274143302}, {"source": 11, "target": 13, "weight": 0.1137071651}, {"source": 11, "target": 12, "weight": 0.1137071651}, {"source": 11, "target": 15, "weight": 0.2274143302}, {"source": 12, "target": 18, "weight": 1.5919003115}, {"source": 12, "target": 15, "weight": 1.023364486}, {"source": 13, "target": 18, "weight": 0.6822429907}, {"source": 13, "target": 14, "weight": 0.4548286604}, {"source": 13, "target": 15, "weight": 3.4112149533}, {"source": 14, "target": 15, "weight": 0.1137071651}, {"source": 15, "target": 18, "weight": 0.1137071651}]}